hestia_earth/earth_engine/__init__.py
hestia_earth/earth_engine/boundary.py
hestia_earth/earth_engine/coordinates.py
hestia_earth/earth_engine/gadm.py
hestia_earth/earth_engine/log.py
hestia_earth/earth_engine/version.py
hestia_earth/earth_engine/utils/__init__.py
hestia_earth/earth_engine/utils/gee.py
hestia_earth/earth_engine/utils/vector.py
hestia_earth/earth_engine/utils/storage/__init__.py
hestia_earth/earth_engine/utils/storage/_azure_client.py
hestia_earth/earth_engine/utils/storage/_local_client.py
hestia_earth/earth_engine/utils/storage/_s3_client.py
hestia_earth_earth_engine-0.6.0.dist-info/licenses/LICENSE
hestia_earth_earth_engine-0.6.0.dist-info/METADATA
hestia_earth_earth_engine-0.6.0.dist-info/WHEEL
hestia_earth_earth_engine-0.6.0.dist-info/top_level.txt
hestia_earth_earth_engine-0.6.0.dist-info/RECORD
