Metadata-Version: 2.4
Name: hestia_earth_earth_engine
Version: 0.6.0
Summary: Hestia's earth engine.
Home-page: https://gitlab.com/hestia-earth/hestia-earth-engine
Author: Hestia Team
Author-email: guillaume@hestia.earth
License: MIT
Classifier: Programming Language :: Python :: 3.12
Requires-Python: >=3.12
License-File: LICENSE
Requires-Dist: hestia-earth-utils>=0.16.1
Requires-Dist: google-api-python-client>=2
Requires-Dist: earthengine-api
Provides-Extra: geopandas
Requires-Dist: shapely; extra == "geopandas"
Requires-Dist: geopandas; extra == "geopandas"
Dynamic: author
Dynamic: author-email
Dynamic: classifier
Dynamic: description
Dynamic: description-content-type
Dynamic: home-page
Dynamic: license
Dynamic: license-file
Dynamic: provides-extra
Dynamic: requires-dist
Dynamic: requires-python
Dynamic: summary
